pysipp/__init__.py
pysipp/agent.py
pysipp/command.py
pysipp/hookspec.py
pysipp/launch.py
pysipp/load.py
pysipp/netplug.py
pysipp/plugin.py
pysipp/report.py
pysipp/utils.py
pysipp/cli/__init__.py
pysipp/cli/minidom.py
pysipp/cli/sippfmt.py
pysipp-0.1.0.dist-info/LICENSE
pysipp-0.1.0.dist-info/METADATA
pysipp-0.1.0.dist-info/WHEEL
pysipp-0.1.0.dist-info/entry_points.txt
pysipp-0.1.0.dist-info/top_level.txt
pysipp-0.1.0.dist-info/RECORD
