Metadata-Version: 2.1
Name: pysipp
Version: 0.1.0
Summary: A SIPp scenario launcher
Home-page: https://github.com/SIPp/pysipp
Author: Tyler Goodlet
Author-email: jgbt@protonmail.com
License: GPLv2
Platform: linux
Classifier: Development Status :: 3 - Alpha
Classifier: Intended Audience :: Developers
Classifier: License :: OSI Approved :: GNU General Public License v2 (GPLv2)
Classifier: Operating System :: POSIX :: Linux
Classifier: Programming Language :: Python :: 2.7
Classifier: Topic :: Software Development
Classifier: Topic :: Software Development :: Testing
Classifier: Topic :: Software Development :: Quality Assurance
Classifier: Topic :: Utilities
Requires-Dist: pluggy (>=0.11.0)
